smllib/__init__.py
smllib/__version__.py
smllib/const.py
smllib/errors.py
smllib/py.typed
smllib/reader.py
smllib/sml_frame.py
smllib/sml_frame_snippet.py
smllib/builder/__init__.py
smllib/builder/_builder.py
smllib/builder/default_context.py
smllib/builder/list_entry.py
smllib/builder/message.py
smllib/builder/response_get_list.py
smllib/builder/response_open_close.py
smllib/crc/__init__.py
smllib/crc/kermit.py
smllib/crc/x25.py
smllib/sml/__init__.py
smllib/sml/_base_obj.py
smllib/sml/_field_info.py
smllib/sml/list_entry.py
smllib/sml/message.py
smllib/sml/response_get_list.py
smllib/sml/response_open_close.py
smllib/sml/sml_choice.py
smllib/sml/sml_eom.py
smllib/sml/sml_obis.py
smllib/sml/sml_time.py
smllib/sml/sml_value.py
smllib-1.7.dist-info/licenses/LICENSE
smllib-1.7.dist-info/METADATA
smllib-1.7.dist-info/WHEEL
smllib-1.7.dist-info/top_level.txt
smllib-1.7.dist-info/RECORD
