Metadata-Version: 2.4
Name: smllib
Version: 1.7
Summary: A library for the SML (Smart Message Language) protocol
Home-page: https://github.com/spacemanspiff2007/SmlLib
Author: spaceman_spiff
Project-URL: GitHub, https://github.com/spacemanspiff2007/SmlLib
Keywords: sml,obis,smart message language,energy meter
Classifier: Development Status :: 4 - Beta
Classifier: License :: OSI Approved :: GNU General Public License v3 or later (GPLv3+)
Classifier: Operating System :: OS Independent
Classifier: Programming Language :: Python :: 3.8
Classifier: Programming Language :: Python :: 3.9
Classifier: Programming Language :: Python :: 3.10
Classifier: Programming Language :: Python :: 3.11
Classifier: Programming Language :: Python :: 3.12
Classifier: Programming Language :: Python :: 3.13
Classifier: Programming Language :: Python :: 3 :: Only
Classifier: Topic :: Home Automation
License-File: LICENSE
Dynamic: author
Dynamic: classifier
Dynamic: description
Dynamic: description-content-type
Dynamic: home-page
Dynamic: keywords
Dynamic: license-file
Dynamic: project-url
Dynamic: summary
